LICENSE
MANIFEST.in
README.md
pyproject.toml
setup.cfg
setup.py
src/napari_vemseg/__init__.py
src/napari_vemseg/napari.yaml
src/napari_vemseg/phh_predict.py
src/napari_vemseg/predict_pixel_classifier.py
src/napari_vemseg/utils.py
src/napari_vemseg/vem_pixel_classifier.py
src/napari_vemseg.egg-info/PKG-INFO
src/napari_vemseg.egg-info/SOURCES.txt
src/napari_vemseg.egg-info/dependency_links.txt
src/napari_vemseg.egg-info/entry_points.txt
src/napari_vemseg.egg-info/requires.txt
src/napari_vemseg.egg-info/top_level.txt
src/napari_vemseg/models/.DS_Store
src/napari_vemseg/models/Standard_UNet/Standard_UNet.py
src/napari_vemseg/resources/VEMSEG-FINAL-WHITE.svg
src/napari_vemseg/resources/VEMSEG-WHITE-OG-RES.png